meteoBrain/__init__.py
meteoBrain/meteoBrain.py
meteoBrain/db/__init__.py
meteoBrain/predict/__init__.py
meteoBrain-0.0.1.dist-info/LICENSE
meteoBrain-0.0.1.dist-info/METADATA
meteoBrain-0.0.1.dist-info/WHEEL
meteoBrain-0.0.1.dist-info/top_level.txt
meteoBrain-0.0.1.dist-info/RECORD
